violit/__init__.py
violit/app.py
violit/broadcast.py
violit/broadcast_primitives.py
violit/component.py
violit/context.py
violit/engine.py
violit/state.py
violit/theme.py
violit/widgets/__init__.py
violit/widgets/card_widgets.py
violit/widgets/chart_widgets.py
violit/widgets/chat_widgets.py
violit/widgets/data_widgets.py
violit/widgets/form_widgets.py
violit/widgets/input_widgets.py
violit/widgets/layout_widgets.py
violit/widgets/list_widgets.py
violit/widgets/media_widgets.py
violit/widgets/status_widgets.py
violit/widgets/text_widgets.py
violit-0.0.5.dist-info/licenses/LICENSE
violit-0.0.5.dist-info/METADATA
violit-0.0.5.dist-info/WHEEL
violit-0.0.5.dist-info/top_level.txt
violit-0.0.5.dist-info/RECORD
