Metadata-Version: 2.4
Name: violit
Version: 0.0.5
Summary: Violit: Faster than Light, Beautiful as Violet. The High-Performance Python Web Framework (Streamlit Alternative with Zero Rerun).
Author-email: Violit Team <violit.company@gmail.com>
License: MIT
Project-URL: Homepage, https://github.com/violit-dev/violit
Project-URL: Documentation, https://github.com/violit-dev/violit
Project-URL: Repository, https://github.com/violit-dev/violit
Project-URL: Issues, https://github.com/violit-dev/violit/issues
Keywords: web,framework,streamlit,dashboard,ui,fastapi,reactive,zero-rerun,shoelace,websocket,data-science
Classifier: Development Status :: 2 - Pre-Alpha
Classifier: Intended Audience :: Developers
Classifier: Intended Audience :: Science/Research
Classifier: License :: OSI Approved :: MIT License
Classifier: Operating System :: OS Independent
Classifier: Programming Language :: Python :: 3
Classifier: Programming Language :: Python :: 3.10
Classifier: Programming Language :: Python :: 3.11
Classifier: Programming Language :: Python :: 3.12
Classifier: Topic :: Internet :: WWW/HTTP :: Dynamic Content
Classifier: Topic :: Software Development :: Libraries :: Application Frameworks
Classifier: Topic :: Software Development :: User Interfaces
Classifier: Framework :: FastAPI
Requires-Python: >=3.10
License-File: LICENSE
Requires-Dist: fastapi>=0.68.0
Requires-Dist: uvicorn>=0.15.0
Requires-Dist: python-multipart>=0.0.5
Requires-Dist: pywebview>=4.0.0
Requires-Dist: cachetools>=4.2.0
Requires-Dist: pandas>=1.3.0
Requires-Dist: numpy>=1.20.0
Requires-Dist: plotly>=5.0.0
Requires-Dist: matplotlib>=3.4.0
Requires-Dist: jinja2>=3.0.0
Requires-Dist: websockets>=10.0
Requires-Dist: bcrypt>=4.0.0
Dynamic: license-file
